[{
        "perm_name": "owner",
        "parent": "",
        "required_auth": {
            "threshold": 1,
            "keys": [{
                "key": "7NFuBesBKK5XHHLtzFxm7S57Eq11gUtndrsvq3Mt3XZNMTHfqc",
                "weight": 1
            }],
            "accounts": [],
            "waits": []
        }
    },
    {
        "perm_name": "active",
        "parent": "owner",
        "required_auth": {
            "threshold": 1,
            "keys": [{
                "key": "7idX86zQ6M3mrzkGQ9MGHf4btSECmcTj4i8Le59ga7CpSpZYy5",
                "weight": 1
            }, {
                "key": "7G5AXPP4RNG5DiZACneMZVenYEQ2GmVwcYUis8YrFHorQic5h8",
                "weight": 1
            }, {
                "key": "88app6Y3DMMa2zFYXtuUZokyZjijN6Pr4W8HgJSmaW8aXgHXp4",
                "weight": 1
            }],
            "accounts": [],
            "waits": []
        }
    }
]